<?xml version="1.0" encoding="UTF-8" standalone="yes"?>
<persistence xmlns="https://jakarta.ee/xml/ns/persistence"
             xmlns:xsi="http://www.w3.org/2001/XMLSchema-instance"
             xsi:schemaLocation="https://jakarta.ee/xml/ns/persistence https://jakarta.ee/xml/ns/persistence/persistence_3_0.xsd"
             version="3.0">
  <persistence-unit name="default">

      <class>com.example.szeleromu.model.Helyszin</class>
      <class>com.example.szeleromu.model.Megye</class>
      <class>com.example.szeleromu.model.Torony</class>
      <class>com.example.szeleromu.model.Webuser</class>
      <class>com.example.szeleromu.model.Contact</class>
      <properties>
          <property name="hibernate.connection.url"
                    value="jdbc:sqlserver://szeleromu.database.windows.net:1433;database=szeleromu;user=CloudSA65387f66@szeleromu;password=Szeleromu00;encrypt=true;trustServerCertificate=false;hostNameInCertificate=*.database.windows.net;loginTimeout=30;"/>
          <property name="hibernate.connection.driver_class" value="com.microsoft.sqlserver.jdbc.SQLServerDriver"/>
      </properties>
  </persistence-unit>
</persistence>
